harambot/bot.py
harambot/cogs/meta.py
harambot/cogs/misc.py
harambot/cogs/yahoo.py
harambot/config.py
harambot/database/fields.py
harambot/database/migrations.py
harambot/database/models.py
harambot/services/reports.py
harambot/services/webserver.py
harambot/ui/modals.py
harambot/ui/views.py
harambot/utils.py
harambot/yahoo_api.py
harambot-0.5.2.post2.dist-info/LICENSE.md
harambot-0.5.2.post2.dist-info/METADATA
harambot-0.5.2.post2.dist-info/WHEEL
harambot-0.5.2.post2.dist-info/entry_points.txt
harambot-0.5.2.post2.dist-info/RECORD
