Metadata-Version: 2.3
Name: harambot
Version: 0.5.2.post2
Summary: A Yahoo Fantasy Sports bot for Discord
License: MIT
Keywords: yahoo,yahoo fantasy sports,fantasy football,fantasy basketball,fantasy baseball,fantasy hockey,discord,bot
Author: DMcP89
Author-email: davemcpherson@wochstudios.com
Requires-Python: >=3.10,<4.0
Classifier: License :: OSI Approved :: MIT License
Classifier: Programming Language :: Python :: 3
Classifier: Programming Language :: Python :: 3.10
Classifier: Programming Language :: Python :: 3.11
Classifier: Programming Language :: Python :: 3.12
Classifier: Programming Language :: Python :: 3.13
Requires-Dist: aiohttp (==3.12.14)
Requires-Dist: cachetools (>=5.5.2,<6.0.0)
Requires-Dist: cryptography (>=44.0.2,<45.0.0)
Requires-Dist: discord.py (>=2.5.2,<3.0.0)
Requires-Dist: dynaconf (>=3.2.10,<4.0.0)
Requires-Dist: mysqlclient (>=2.2.7,<3.0.0)
Requires-Dist: peewee (>=3.17.9,<4.0.0)
Requires-Dist: psycopg2 (>=2.9.10,<3.0.0)
Requires-Dist: requests (==2.32.4)
Requires-Dist: urllib3 (==2.5.0)
Requires-Dist: yahoo-fantasy-api (>=2.11.0,<3.0.0)
Requires-Dist: yahoo-oauth (>=2.1.1,<3.0.0)
Project-URL: Homepage, http://harambot.io
Project-URL: Repository, https://github.com/DMcP89/harambot
